{"ILCH Combined Dataset": [{"sourced_from": "./sources/ilchtablestemplatesa.xls", "id": "./sources/ilchtablestemplatesa.xls : 3. Industry annual growth SA", "tab": "3. Industry annual growth SA", "column_actions": [{"column_id": "Geography", "column_label": "Geography", "actions": [{"2020-06-04 09:50:04.767184": "Hard code to K02000001"}, {"2020-06-04 09:50:06.276304": "ALL: Stored under the identifier 'combined ilch dataframes'"}, {"2020-06-04 09:50:10.319767": "Concatenated into datacube 'combined ilch dataframes'"}]}, {"column_id": "Time", "column_label": "Time", "actions": [{"2020-06-04 09:50:04.767193": "Is in column A"}, {"2020-06-04 09:50:06.276334": "ALL: Stored under the identifier 'combined ilch dataframes'"}, {"2020-06-04 09:50:10.319793": "Concatenated into datacube 'combined ilch dataframes'"}]}, {"column_id": "Seasonal_Adjustment", "column_label": "Seasonal Adjustment", "actions": [{"2020-06-04 09:50:04.767152": "Hard code to Seasonally adjusted"}, {"2020-06-04 09:50:06.276343": "ALL: Stored under the identifier 'combined ilch dataframes'"}, {"2020-06-04 09:50:10.319801": "Concatenated into datacube 'combined ilch dataframes'"}]}, {"column_id": "Growth_Type", "column_label": "Growth Type", "actions": [{"2020-06-04 09:50:06.276349": "ALL: Stored under the identifier 'combined ilch dataframes'"}, {"2020-06-04 09:50:10.319808": "Concatenated into datacube 'combined ilch dataframes'"}]}, {"column_id": "Labour", "column_label": "Labour", "actions": [{"2020-06-04 09:50:04.767404": "Select whatevers in cell A1"}, {"2020-06-04 09:50:06.276355": "ALL: Stored under the identifier 'combined ilch dataframes'"}, {"2020-06-04 09:50:10.319814": "Concatenated into datacube 'combined ilch dataframes'"}]}, {"column_id": "Indicator", "column_label": "Indicator", "actions": [{"2020-06-04 09:50:06.276361": "ALL: Stored under the identifier 'combined ilch dataframes'"}, {"2020-06-04 09:50:10.319821": "Concatenated into datacube 'combined ilch dataframes'"}]}], "preview": "documentation/previews/d9a95d3e-7be7-40e2-a76a-3b045859f029.html"}, {"sourced_from": "./sources/ilchtablestemplatesa.xls", "id": "./sources/ilchtablestemplatesa.xls : 4. Sector annual growth SA", "tab": "4. Sector annual growth SA", "column_actions": [{"column_id": "Geography", "column_label": "Geography", "actions": [{"2020-06-04 09:50:06.276414": "Hard code to K02000001"}, {"2020-06-04 09:50:06.858178": "ALL: Stored under the identifier 'combined ilch dataframes'"}, {"2020-06-04 09:50:10.319828": "Concatenated into datacube 'combined ilch dataframes'"}]}, {"column_id": "Time", "column_label": "Time", "actions": [{"2020-06-04 09:50:06.276421": "Is in column A"}, {"2020-06-04 09:50:06.858206": "ALL: Stored under the identifier 'combined ilch dataframes'"}, {"2020-06-04 09:50:10.319835": "Concatenated into datacube 'combined ilch dataframes'"}]}, {"column_id": "Seasonal_Adjustment", "column_label": "Seasonal Adjustment", "actions": [{"2020-06-04 09:50:06.276405": "Hard code to Seasonally adjusted"}, {"2020-06-04 09:50:06.858214": "ALL: Stored under the identifier 'combined ilch dataframes'"}, {"2020-06-04 09:50:10.319841": "Concatenated into datacube 'combined ilch dataframes'"}]}, {"column_id": "Growth_Type", "column_label": "Growth Type", "actions": [{"2020-06-04 09:50:06.858220": "ALL: Stored under the identifier 'combined ilch dataframes'"}, {"2020-06-04 09:50:10.319848": "Concatenated into datacube 'combined ilch dataframes'"}]}, {"column_id": "Labour", "column_label": "Labour", "actions": [{"2020-06-04 09:50:06.276453": "Select whatevers in cell A1"}, {"2020-06-04 09:50:06.858226": "ALL: Stored under the identifier 'combined ilch dataframes'"}, {"2020-06-04 09:50:10.319854": "Concatenated into datacube 'combined ilch dataframes'"}]}, {"column_id": "Indicator", "column_label": "Indicator", "actions": [{"2020-06-04 09:50:06.858232": "ALL: Stored under the identifier 'combined ilch dataframes'"}, {"2020-06-04 09:50:10.319861": "Concatenated into datacube 'combined ilch dataframes'"}]}], "preview": "documentation/previews/20a5f418-79ec-4df1-b5a3-74ea68b6eebf.html"}, {"sourced_from": "./sources/ilchtablestemplatesa.xls", "id": "./sources/ilchtablestemplatesa.xls : 5. Industry quarterly growth SA", "tab": "5. Industry quarterly growth SA", "column_actions": [{"column_id": "Geography", "column_label": "Geography", "actions": [{"2020-06-04 09:50:06.858288": "Hard code to K02000001"}, {"2020-06-04 09:50:07.600832": "ALL: Stored under the identifier 'combined ilch dataframes'"}, {"2020-06-04 09:50:10.319868": "Concatenated into datacube 'combined ilch dataframes'"}]}, {"column_id": "Time", "column_label": "Time", "actions": [{"2020-06-04 09:50:06.858295": "Is in column A"}, {"2020-06-04 09:50:07.600859": "ALL: Stored under the identifier 'combined ilch dataframes'"}, {"2020-06-04 09:50:10.319875": "Concatenated into datacube 'combined ilch dataframes'"}]}, {"column_id": "Seasonal_Adjustment", "column_label": "Seasonal Adjustment", "actions": [{"2020-06-04 09:50:06.858278": "Hard code to Seasonally adjusted"}, {"2020-06-04 09:50:07.600867": "ALL: Stored under the identifier 'combined ilch dataframes'"}, {"2020-06-04 09:50:10.319881": "Concatenated into datacube 'combined ilch dataframes'"}]}, {"column_id": "Growth_Type", "column_label": "Growth Type", "actions": [{"2020-06-04 09:50:07.600873": "ALL: Stored under the identifier 'combined ilch dataframes'"}, {"2020-06-04 09:50:10.319888": "Concatenated into datacube 'combined ilch dataframes'"}]}, {"column_id": "Labour", "column_label": "Labour", "actions": [{"2020-06-04 09:50:06.858330": "Select whatevers in cell A1"}, {"2020-06-04 09:50:07.600879": "ALL: Stored under the identifier 'combined ilch dataframes'"}, {"2020-06-04 09:50:10.319894": "Concatenated into datacube 'combined ilch dataframes'"}]}, {"column_id": "Indicator", "column_label": "Indicator", "actions": [{"2020-06-04 09:50:07.600885": "ALL: Stored under the identifier 'combined ilch dataframes'"}, {"2020-06-04 09:50:10.319900": "Concatenated into datacube 'combined ilch dataframes'"}]}], "preview": "documentation/previews/bd9b29e9-02a0-4b98-b321-d4a99a7f1798.html"}, {"sourced_from": "./sources/ilchtablestemplatesa.xls", "id": "./sources/ilchtablestemplatesa.xls : 6. Sector quarterly growth SA", "tab": "6. Sector quarterly growth SA", "column_actions": [{"column_id": "Geography", "column_label": "Geography", "actions": [{"2020-06-04 09:50:07.600937": "Hard code to K02000001"}, {"2020-06-04 09:50:08.169902": "ALL: Stored under the identifier 'combined ilch dataframes'"}, {"2020-06-04 09:50:10.319907": "Concatenated into datacube 'combined ilch dataframes'"}]}, {"column_id": "Time", "column_label": "Time", "actions": [{"2020-06-04 09:50:07.600944": "Is in column A"}, {"2020-06-04 09:50:08.169928": "ALL: Stored under the identifier 'combined ilch dataframes'"}, {"2020-06-04 09:50:10.319914": "Concatenated into datacube 'combined ilch dataframes'"}]}, {"column_id": "Seasonal_Adjustment", "column_label": "Seasonal Adjustment", "actions": [{"2020-06-04 09:50:07.600928": "Hard code to Seasonally adjusted"}, {"2020-06-04 09:50:08.169935": "ALL: Stored under the identifier 'combined ilch dataframes'"}, {"2020-06-04 09:50:10.319921": "Concatenated into datacube 'combined ilch dataframes'"}]}, {"column_id": "Growth_Type", "column_label": "Growth Type", "actions": [{"2020-06-04 09:50:08.169941": "ALL: Stored under the identifier 'combined ilch dataframes'"}, {"2020-06-04 09:50:10.319927": "Concatenated into datacube 'combined ilch dataframes'"}]}, {"column_id": "Labour", "column_label": "Labour", "actions": [{"2020-06-04 09:50:07.600976": "Select whatevers in cell A1"}, {"2020-06-04 09:50:08.169947": "ALL: Stored under the identifier 'combined ilch dataframes'"}, {"2020-06-04 09:50:10.319933": "Concatenated into datacube 'combined ilch dataframes'"}]}, {"column_id": "Indicator", "column_label": "Indicator", "actions": [{"2020-06-04 09:50:08.169953": "ALL: Stored under the identifier 'combined ilch dataframes'"}, {"2020-06-04 09:50:10.319940": "Concatenated into datacube 'combined ilch dataframes'"}]}], "preview": "documentation/previews/acabac70-f7ea-42b3-8e78-7eb90752c1b0.html"}, {"sourced_from": "./sources/ilchtablestemplatensa.xls", "id": "./sources/ilchtablestemplatensa.xls : 3. Industry growth rates", "tab": "3. Industry growth rates", "column_actions": [{"column_id": "Geography", "column_label": "Geography", "actions": [{"2020-06-04 09:50:08.743683": "Hard code to K02000001"}, {"2020-06-04 09:50:09.518243": "ALL: Stored under the identifier 'combined ilch dataframes'"}, {"2020-06-04 09:50:10.319947": "Concatenated into datacube 'combined ilch dataframes'"}]}, {"column_id": "Time", "column_label": "Time", "actions": [{"2020-06-04 09:50:08.743692": "Is in column A"}, {"2020-06-04 09:50:09.518270": "ALL: Stored under the identifier 'combined ilch dataframes'"}, {"2020-06-04 09:50:10.319953": "Concatenated into datacube 'combined ilch dataframes'"}]}, {"column_id": "Seasonal_Adjustment", "column_label": "Seasonal Adjustment", "actions": [{"2020-06-04 09:50:08.743649": "Hard code to Not Seasonally adjusted"}, {"2020-06-04 09:50:09.518278": "ALL: Stored under the identifier 'combined ilch dataframes'"}, {"2020-06-04 09:50:10.319960": "Concatenated into datacube 'combined ilch dataframes'"}]}, {"column_id": "Growth_Type", "column_label": "Growth Type", "actions": [{"2020-06-04 09:50:09.518284": "ALL: Stored under the identifier 'combined ilch dataframes'"}, {"2020-06-04 09:50:10.319966": "Concatenated into datacube 'combined ilch dataframes'"}]}, {"column_id": "Labour", "column_label": "Labour", "actions": [{"2020-06-04 09:50:08.743726": "Select whatevers in cell A1"}, {"2020-06-04 09:50:09.518290": "ALL: Stored under the identifier 'combined ilch dataframes'"}, {"2020-06-04 09:50:10.319972": "Concatenated into datacube 'combined ilch dataframes'"}]}, {"column_id": "Indicator", "column_label": "Indicator", "actions": [{"2020-06-04 09:50:09.518296": "ALL: Stored under the identifier 'combined ilch dataframes'"}, {"2020-06-04 09:50:10.319979": "Concatenated into datacube 'combined ilch dataframes'"}]}], "preview": "documentation/previews/6f083c8e-3d26-4eee-898f-105715bebf53.html"}, {"sourced_from": "./sources/ilchtablestemplatensa.xls", "id": "./sources/ilchtablestemplatensa.xls : 4. Sector growth rates", "tab": "4. Sector growth rates", "column_actions": [{"column_id": "Geography", "column_label": "Geography", "actions": [{"2020-06-04 09:50:09.518349": "Hard code to K02000001"}, {"2020-06-04 09:50:09.802098": "ALL: Stored under the identifier 'combined ilch dataframes'"}, {"2020-06-04 09:50:10.319986": "Concatenated into datacube 'combined ilch dataframes'"}]}, {"column_id": "Time", "column_label": "Time", "actions": [{"2020-06-04 09:50:09.518356": "Is in column A"}, {"2020-06-04 09:50:09.802127": "ALL: Stored under the identifier 'combined ilch dataframes'"}, {"2020-06-04 09:50:10.319993": "Concatenated into datacube 'combined ilch dataframes'"}]}, {"column_id": "Seasonal_Adjustment", "column_label": "Seasonal Adjustment", "actions": [{"2020-06-04 09:50:09.518340": "Hard code to Not Seasonally adjusted"}, {"2020-06-04 09:50:09.802135": "ALL: Stored under the identifier 'combined ilch dataframes'"}, {"2020-06-04 09:50:10.319999": "Concatenated into datacube 'combined ilch dataframes'"}]}, {"column_id": "Growth_Type", "column_label": "Growth Type", "actions": [{"2020-06-04 09:50:09.802142": "ALL: Stored under the identifier 'combined ilch dataframes'"}, {"2020-06-04 09:50:10.320006": "Concatenated into datacube 'combined ilch dataframes'"}]}, {"column_id": "Labour", "column_label": "Labour", "actions": [{"2020-06-04 09:50:09.518386": "Select whatevers in cell A1"}, {"2020-06-04 09:50:09.802148": "ALL: Stored under the identifier 'combined ilch dataframes'"}, {"2020-06-04 09:50:10.320012": "Concatenated into datacube 'combined ilch dataframes'"}]}, {"column_id": "Indicator", "column_label": "Indicator", "actions": [{"2020-06-04 09:50:09.802154": "ALL: Stored under the identifier 'combined ilch dataframes'"}, {"2020-06-04 09:50:10.320018": "Concatenated into datacube 'combined ilch dataframes'"}]}], "preview": "documentation/previews/d672829b-f512-4acf-8196-b2e2301785ed.html"}, {"sourced_from": "./sources/ilchtablestemplatensa.xls", "id": "./sources/ilchtablestemplatensa.xls : 5. Industry costs", "tab": "5. Industry costs", "column_actions": [{"column_id": "Geography", "column_label": "Geography", "actions": [{"2020-06-04 09:50:09.802208": "Hard code to K02000001"}, {"2020-06-04 09:50:10.186363": "ALL: Stored under the identifier 'combined ilch dataframes'"}, {"2020-06-04 09:50:10.320026": "Concatenated into datacube 'combined ilch dataframes'"}]}, {"column_id": "Time", "column_label": "Time", "actions": [{"2020-06-04 09:50:09.802215": "Is in column A"}, {"2020-06-04 09:50:10.186391": "ALL: Stored under the identifier 'combined ilch dataframes'"}, {"2020-06-04 09:50:10.320032": "Concatenated into datacube 'combined ilch dataframes'"}]}, {"column_id": "Seasonal_Adjustment", "column_label": "Seasonal Adjustment", "actions": [{"2020-06-04 09:50:09.802198": "Hard code to Not Seasonally adjusted"}, {"2020-06-04 09:50:10.186399": "ALL: Stored under the identifier 'combined ilch dataframes'"}, {"2020-06-04 09:50:10.320039": "Concatenated into datacube 'combined ilch dataframes'"}]}, {"column_id": "Growth_Type", "column_label": "Growth Type", "actions": [{"2020-06-04 09:50:10.186406": "ALL: Stored under the identifier 'combined ilch dataframes'"}, {"2020-06-04 09:50:10.320045": "Concatenated into datacube 'combined ilch dataframes'"}]}, {"column_id": "Labour", "column_label": "Labour", "actions": [{"2020-06-04 09:50:09.802248": "Select whatevers in cell A1"}, {"2020-06-04 09:50:10.186412": "ALL: Stored under the identifier 'combined ilch dataframes'"}, {"2020-06-04 09:50:10.320052": "Concatenated into datacube 'combined ilch dataframes'"}]}, {"column_id": "Indicator", "column_label": "Indicator", "actions": [{"2020-06-04 09:50:10.186418": "ALL: Stored under the identifier 'combined ilch dataframes'"}, {"2020-06-04 09:50:10.320058": "Concatenated into datacube 'combined ilch dataframes'"}]}], "preview": "documentation/previews/4b82bc00-990f-4e93-8dff-15f349d73f6d.html"}, {"sourced_from": "./sources/ilchtablestemplatensa.xls", "id": "./sources/ilchtablestemplatensa.xls : 6. Sector costs", "tab": "6. Sector costs", "column_actions": [{"column_id": "Geography", "column_label": "Geography", "actions": [{"2020-06-04 09:50:10.186472": "Hard code to K02000001"}, {"2020-06-04 09:50:10.313109": "ALL: Stored under the identifier 'combined ilch dataframes'"}, {"2020-06-04 09:50:10.320065": "Concatenated into datacube 'combined ilch dataframes'"}]}, {"column_id": "Time", "column_label": "Time", "actions": [{"2020-06-04 09:50:10.186480": "Is in column A"}, {"2020-06-04 09:50:10.313136": "ALL: Stored under the identifier 'combined ilch dataframes'"}, {"2020-06-04 09:50:10.320072": "Concatenated into datacube 'combined ilch dataframes'"}]}, {"column_id": "Seasonal_Adjustment", "column_label": "Seasonal Adjustment", "actions": [{"2020-06-04 09:50:10.186463": "Hard code to Not Seasonally adjusted"}, {"2020-06-04 09:50:10.313145": "ALL: Stored under the identifier 'combined ilch dataframes'"}, {"2020-06-04 09:50:10.320078": "Concatenated into datacube 'combined ilch dataframes'"}]}, {"column_id": "Growth_Type", "column_label": "Growth Type", "actions": [{"2020-06-04 09:50:10.313151": "ALL: Stored under the identifier 'combined ilch dataframes'"}, {"2020-06-04 09:50:10.320084": "Concatenated into datacube 'combined ilch dataframes'"}]}, {"column_id": "Labour", "column_label": "Labour", "actions": [{"2020-06-04 09:50:10.186513": "Select whatevers in cell A1"}, {"2020-06-04 09:50:10.313158": "ALL: Stored under the identifier 'combined ilch dataframes'"}, {"2020-06-04 09:50:10.320091": "Concatenated into datacube 'combined ilch dataframes'"}]}, {"column_id": "Indicator", "column_label": "Indicator", "actions": [{"2020-06-04 09:50:10.313164": "ALL: Stored under the identifier 'combined ilch dataframes'"}, {"2020-06-04 09:50:10.320097": "Concatenated into datacube 'combined ilch dataframes'"}]}], "preview": "documentation/previews/ca7a78bf-c3d7-4de6-9b55-e2546d181402.html"}, {"sourced_from": ["./sources/ilchtablestemplatesa.xls : 3. Industry annual growth SA", "./sources/ilchtablestemplatesa.xls : 4. Sector annual growth SA", "./sources/ilchtablestemplatesa.xls : 5. Industry quarterly growth SA", "./sources/ilchtablestemplatesa.xls : 6. Sector quarterly growth SA", "./sources/ilchtablestemplatensa.xls : 3. Industry growth rates", "./sources/ilchtablestemplatensa.xls : 4. Sector growth rates", "./sources/ilchtablestemplatensa.xls : 5. Industry costs", "./sources/ilchtablestemplatensa.xls : 6. Sector costs"], "id": "combined ilch dataframes", "tab": "combined ilch dataframes", "column_actions": [{"column_id": "Geography", "column_label": "Geography", "actions": [{"2020-06-04 09:50:10.324095": "ALL: Ammend this note to literally everything"}]}, {"column_id": "Time", "column_label": "Time", "actions": [{"2020-06-04 09:50:10.324121": "ALL: Ammend this note to literally everything"}]}, {"column_id": "Seasonal_Adjustment", "column_label": "Seasonal Adjustment", "actions": [{"2020-06-04 09:50:10.324130": "ALL: Ammend this note to literally everything"}]}, {"column_id": "Growth_Type", "column_label": "Growth Type", "actions": [{"2020-06-04 09:50:10.324137": "ALL: Ammend this note to literally everything"}]}, {"column_id": "Labour", "column_label": "Labour", "actions": [{"2020-06-04 09:50:10.324143": "ALL: Ammend this note to literally everything"}]}, {"column_id": "Indicator", "column_label": "Indicator", "actions": [{"2020-06-04 09:50:10.324150": "ALL: Ammend this note to literally everything"}]}]}]}